connect/eaas/core/__init__.py
connect/eaas/core/constants.py
connect/eaas/core/contrib/__init__.py
connect/eaas/core/contrib/django/__init__.py
connect/eaas/core/contrib/django/rql.py
connect/eaas/core/decorators.py
connect/eaas/core/deployment/__init__.py
connect/eaas/core/deployment/extension.py
connect/eaas/core/deployment/helpers.py
connect/eaas/core/deployment/utils.py
connect/eaas/core/enums.py
connect/eaas/core/extension.py
connect/eaas/core/inject/__init__.py
connect/eaas/core/inject/asynchronous.py
connect/eaas/core/inject/common.py
connect/eaas/core/inject/models.py
connect/eaas/core/inject/synchronous.py
connect/eaas/core/logging.py
connect/eaas/core/models.py
connect/eaas/core/proto.py
connect/eaas/core/responses.py
connect/eaas/core/testing/__init__.py
connect/eaas/core/testing/fixtures.py
connect/eaas/core/testing/testclient.py
connect/eaas/core/utils.py
connect/eaas/core/validation/helpers.py
connect/eaas/core/validation/models.py
connect/eaas/core/validation/validators/__init__.py
connect/eaas/core/validation/validators/anvilapp.py
connect/eaas/core/validation/validators/base.py
connect/eaas/core/validation/validators/eventsapp.py
connect/eaas/core/validation/validators/tfnapp.py
connect/eaas/core/validation/validators/webapp.py
connect_eaas_core-37.0.dist-info/LICENSE
connect_eaas_core-37.0.dist-info/METADATA
connect_eaas_core-37.0.dist-info/WHEEL
connect_eaas_core-37.0.dist-info/entry_points.txt
connect_eaas_core-37.0.dist-info/RECORD
