Metadata-Version: 2.3
Name: connect-eaas-core
Version: 37.0
Summary: Connect Eaas Core
License: Apache-2.0
Author: CloudBlue LLC
Requires-Python: >=3.9,<4
Classifier: Development Status :: 5 - Production/Stable
Classifier: Environment :: Console
Classifier: Intended Audience :: Developers
Classifier: License :: OSI Approved :: Apache Software License
Classifier: Operating System :: OS Independent
Classifier: Programming Language :: Python :: 3
Classifier: Programming Language :: Python :: 3.9
Classifier: Programming Language :: Python :: 3.10
Classifier: Programming Language :: Python :: 3.11
Classifier: Programming Language :: Python :: 3.12
Classifier: Programming Language :: Python :: 3.13
Classifier: Topic :: Software Development :: Libraries
Classifier: Topic :: Utilities
Requires-Dist: PyYAML (>=6.0,<7.0)
Requires-Dist: anvil-uplink (>=0.5.2,<0.6.0)
Requires-Dist: connect-openapi-client (>=25.20)
Requires-Dist: fastapi (>=0.115.0,<0.116.0)
Requires-Dist: fastapi-utils (>=0.8.0,<0.9.0)
Requires-Dist: logzio-python-handler (>=3.1.1,<4.2)
Requires-Dist: pydantic (>=1.10,<2.0)
Requires-Dist: toml (>=0.10.2,<0.11.0)
Requires-Dist: typing-extensions (<5)
Project-URL: Homepage, https://connect.cloudblue.com
Project-URL: Repository, https://github.com/cloudblue/connect-eaas-core
